{
  "width": 864,
  "height": 758,
  "cx": [
    [ "CONTENU", 274 ],
    [ "BOITE", 406 ],
    [ "OFFICIEL", 274 ],
    [ "PROPOSE", 406 ],
    [ "AMATEUR", 152 ],
    [ "CONSTRUCTION_PARENT_#1", 274 ],
    [ "USINE", 535 ],
    [ "ETAPE", 51 ],
    [ "SUIVRE", 152 ],
    [ "CONSTRUCTION", 274 ],
    [ "ASSEMBLAGE", 406 ],
    [ "FABRIQUE", 535 ],
    [ "EVOLUTION", 667 ],
    [ "PHOTO", 152 ],
    [ "PHOTO_PARENT_#2", 274 ],
    [ "PIECE", 406 ],
    [ "ENREGISTRE", 535 ],
    [ "CONFIGURATION", 667 ],
    [ "POSSEDER1", 406 ],
    [ "TOURS", 535 ],
    [ "POSSEDE", 667 ],
    [ "JOUEUSE", 793 ],
    [ "SUBSTITUTION", 406 ],
    [ "COMPRENDRE", 535 ],
    [ "PARTIE", 667 ],
    [ "DEROULER", 793 ]
  ],
  "cy": [
    [ "CONTENU", 51 ],
    [ "BOITE", 51 ],
    [ "OFFICIEL", 143 ],
    [ "PROPOSE", 143 ],
    [ "AMATEUR", 227 ],
    [ "CONSTRUCTION_PARENT_#1", 227 ],
    [ "USINE", 227 ],
    [ "ETAPE", 345 ],
    [ "SUIVRE", 345 ],
    [ "CONSTRUCTION", 345 ],
    [ "ASSEMBLAGE", 345 ],
    [ "FABRIQUE", 345 ],
    [ "EVOLUTION", 345 ],
    [ "PHOTO", 471 ],
    [ "PHOTO_PARENT_#2", 471 ],
    [ "PIECE", 471 ],
    [ "ENREGISTRE", 471 ],
    [ "CONFIGURATION", 471 ],
    [ "POSSEDER1", 580 ],
    [ "TOURS", 580 ],
    [ "POSSEDE", 580 ],
    [ "JOUEUSE", 580 ],
    [ "SUBSTITUTION", 698 ],
    [ "COMPRENDRE", 698 ],
    [ "PARTIE", 698 ],
    [ "DEROULER", 698 ]
  ],
  "shift": [
    [ "CONTENU,BOITE,0", 0 ],
    [ "CONTENU,OFFICIEL,0", 0 ],
    [ "PROPOSE,OFFICIEL,0", 0 ],
    [ "PROPOSE,USINE,0", 0 ],
    [ "SUIVRE,CONSTRUCTION,0", 0 ],
    [ "SUIVRE,ETAPE,0", 0 ],
    [ "ASSEMBLAGE,CONSTRUCTION,0", 0 ],
    [ "ASSEMBLAGE,PIECE,0", 0 ],
    [ "FABRIQUE,USINE,0", 0 ],
    [ "FABRIQUE,PIECE,0", 0 ],
    [ "EVOLUTION,CONFIGURATION,-1_0", 0 ],
    [ "EVOLUTION,CONFIGURATION,1_0", 0 ],
    [ "ENREGISTRE,PIECE,0", 0 ],
    [ "ENREGISTRE,TOURS,0", 0 ],
    [ "POSSEDER1,PIECE,0", 0 ],
    [ "POSSEDER1,SUBSTITUTION,0", 0 ],
    [ "POSSEDE,PARTIE,0", 0 ],
    [ "POSSEDE,CONFIGURATION,0", 0 ],
    [ "COMPRENDRE,TOURS,0", 0 ],
    [ "COMPRENDRE,PARTIE,0", 0 ],
    [ "DEROULER,PARTIE,0", 0 ],
    [ "DEROULER,JOUEUSE,0", 0 ]
  ],
  "ratio": [
    [ "CONSTRUCTION_PARENT_#1 / AMATEUR", 1.0 ],
    [ "CONSTRUCTION_PARENT_#1 / OFFICIEL", 1.0 ],
    [ "PHOTO_PARENT_#2 / CONSTRUCTION", 1.0 ],
    [ "PHOTO_PARENT_#2 / PIECE", 1.0 ]
  ]
}
